rusrul_lib/__init__.py
rusrul_lib/main.py
rusrul_lib-1.1.dist-info/METADATA
rusrul_lib-1.1.dist-info/WHEEL
rusrul_lib-1.1.dist-info/top_level.txt
rusrul_lib-1.1.dist-info/RECORD
