Metadata-Version: 2.2
Name: rusrul_lib
Version: 1.1
Summary: Adds a revolver class for playing russian roulette with python.
Keywords: silly,random,russian roulette,русская рулетка
